{
    "md5-cpp-install-openssl-0002": "在您的系統上安裝 OpenSSL，並在建置 C++ 應用程式時連結「libssl」和「libcrypto」函式庫。",
    "md5-cpp-openssl-0001": "C++ 使用 OpenSSL 函式庫產生 MD5 雜湊值。您需要安裝 OpenSSL 並在專案中連結它。",
    "md5-cpp-use-openssl-0003": "該程式碼片段建立一個函數“getMD5”，該函數接受輸入字串，使用 OpenSSL 的 MD5 API 計算其 MD5 雜湊值，並將雜湊值作為十六進位字串傳回。將此程式碼貼到您的 C++ 程式中，並使用所需的輸入呼叫“getMD5”函數。",
    "md5-csharp-built-in-0001": "在 C# 中，「System.Security.Cryptography.MD5」類別用於產生 MD5 哈希值。",
    "md5-csharp-no-install-0002": "不需要安裝外部函式庫，因為它是 .NET Framework/Core 的一部分。",
    "md5-csharp-use-0003": "此程式碼片段建立一個 MD5 實例，將輸入字串轉換為位元組，計算雜湊值，最後以 Base64 格式對雜湊值進行編碼。將此程式碼放入 C# 應用程式的入口點並執行它以取得 Base64 編碼的 MD5 雜湊值。",
    "md5-java-built-in-0001": "Java 使用「java.security.MessageDigest」類別來產生 MD5 雜湊值。",
    "md5-java-imports-0002": "您需要匯入“java.security.MessageDigest”和“java.util.Base64”以對結果進行雜湊和編碼。",
    "md5-java-use-0003": "此程式碼片段取得 MD5 摘要演算法的實例，使用輸入字串的位元組更新它，然後將產生的雜湊值編碼為 Base64 字串。將此程式碼複製到 Java 類別中並執行其 main 方法以取得 Base64 編碼的 MD5 雜湊值。",
    "md5-nodejs-built-in-0001": "在 Node.js 中，內建的「crypto」模組用於產生 MD5 哈希值。",
    "md5-nodejs-no-install-0002": "無需安裝外部函式庫，因為「crypto」已隨 Node.js 預先安裝。",
    "md5-nodejs-use-0003": "程式碼片段使用 createHash('md5') 建立一個雜湊對象，使用輸入字串更新它，然後透過 .digest('hex') 將摘要轉換為十六進位格式。將此程式碼貼到 Node.js 腳本中並執行它以獲取輸入值的 MD5 哈希值。",
    "md5-php-built-in-0001": "PHP 有一個內建函數「md5()」用於產生 MD5 雜湊值。",
    "md5-php-no-install-0002": "無需安裝外部函式庫，因為 PHP 中已預先安裝“md5()”。",
    "md5-php-use-0003": "這個簡單的範例定義了一個「getMD5」函數，該函數對提供的輸入字串呼叫 PHP「md5()」函數。將此程式碼複製到 PHP 檔案中，使用 .php 副檔名儲存，然後在 Web 伺服器中或透過命令列運行它以查看輸入值的 MD5 雜湊值。",
    "md5-python-built-in-0001": "Python 使用內建的「hashlib」函式庫來產生 MD5 雜湊值。",
    "md5-python-no-install-0002": "無需額外安裝，因為「hashlib」是 Python 的標準配置。",
    "md5-python-use-0003": "提供的模板在創建 MD5 雜湊物件之前將輸入字串編碼為位元組。然後對雜湊物件呼叫“.hexdigest()”方法以檢索十六進位形式的 MD5 雜湊值。將此程式碼複製到 Python 腳本中並運行它以獲取 MD5 哈希值。"
}